[
  {
    "start": 0.0,
    "end": 29.09,
    "b_start": 0.0,
    "b_end": 48.52,
    "orig": "22 juni. Jag sitter och läser bladet som jag skref\ni går afton, läser det om och om igen, och jag\nsäger till mig själf: så, gamle vän, du har alltså\nblifvit kopplare? Dumheter. Jag har befriat henne ur något\nförfärligt. Jag kände det som något som måste\ngöras.",
    "en": "June 22. I sit and read the sheet I wrote last night, read it over and over, and I say to myself: so, old friend, you have become a coupler? Nonsense. I have freed her from something terrible. I felt it as something that had to be done."
  },
  {
    "start": 30.09,
    "end": 33.54,
    "b_start": 48.52,
    "b_end": 56.62,
    "orig": "Hvad hon så gör med sig själf är hennes sak.",
    "en": "What she does with herself is her business."
  }
]